openweather_sdk/__init__.py
openweather_sdk/cache.py
openweather_sdk/exceptions.py
openweather_sdk/globals.py
openweather_sdk/logger_filters.py
openweather_sdk/validators.py
openweather_sdk/rest/__init__.py
openweather_sdk/rest/airpollution.py
openweather_sdk/rest/base.py
openweather_sdk/rest/forecast.py
openweather_sdk/rest/geocoding.py
openweather_sdk/rest/openweather.py
openweather_sdk/rest/weather.py
msklv_openweather_sdk-1.1.1.dist-info/LICENSE
msklv_openweather_sdk-1.1.1.dist-info/METADATA
msklv_openweather_sdk-1.1.1.dist-info/WHEEL
msklv_openweather_sdk-1.1.1.dist-info/top_level.txt
msklv_openweather_sdk-1.1.1.dist-info/RECORD
