Metadata-Version: 2.1
Name: msklv-openweather-sdk
Version: 1.1.1
Summary: SDK for accessing to OpenWeatherAPI
Home-page: https://github.com/maskalev/openweather_sdk
Author-email: Aleksandr Maskalev <avmaskalev@gmail.com>
License: MIT License
Project-URL: Homepage, https://github.com/maskalev/openweather_sdk
Project-URL: Changelog, https://github.com/maskalev/openweather_sdk/blob/master/CHANGELOG.md
Keywords: weather,sdk,openweather
Platform: UNKNOWN
Classifier: License :: OSI Approved :: MIT License
Classifier: Programming Language :: Python :: 3.7
Classifier: Programming Language :: Python :: 3.8
Classifier: Programming Language :: Python :: 3.9
Classifier: Programming Language :: Python :: 3.10
Classifier: Programming Language :: Python :: 3.11
Classifier: Programming Language :: Python :: 3.12
Classifier: Development Status :: 5 - Production/Stable
Requires-Python: >=3.7
License-File: LICENSE
Requires-Dist: requests<2.33,>=2.31
Provides-Extra: dev
Requires-Dist: black; extra == "dev"
Requires-Dist: bumpver; extra == "dev"
Requires-Dist: freezegun; extra == "dev"
Requires-Dist: isort; extra == "dev"
Requires-Dist: pytest; extra == "dev"
